region_growth/Makefile
region_growth/_GPURegiongrowth.so
region_growth/__init__.py
region_growth/src/regionGrowth.cu
tinavi_medical-0.1.1.dist-info/WHEEL
tinavi_medical-0.1.1.dist-info/METADATA
tinavi_medical-0.1.1.dist-info/RECORD
