Metadata-Version: 2.1
Name: tinavi-medical
Version: 0.1.1
Summary: tinavi utilities for medical image processing
Author: 安兴乐
Author-email: anxingle@163.com
Requires-Python: >=3.8,<4.0
Classifier: Programming Language :: Python :: 3
Classifier: Programming Language :: Python :: 3.8
Classifier: Programming Language :: Python :: 3.9
Classifier: Programming Language :: Python :: 3.10
Classifier: Programming Language :: Python :: 3.11
Requires-Dist: importlib-metadata (>=5.0.0,<6.0.0)
Requires-Dist: numpy (>=1.20.0,<2.0.0)
